{
  "packageDirectories": [
    {
      "versionName": "ver 0.1",
      "versionNumber": "0.1.0.NEXT",
      "path": "force-app",
      "default": true,
      "package": "AmpleFlowEnrichAndSequence",
      "versionDescription": ""
    },
    {
      "versionName": "ver 0.1",
      "versionNumber": "0.1.0.NEXT",
      "path": "force-app",
      "default": false,
      "package": "AmplemarketEnrichAndSequenceFlow",
      "versionDescription": ""
    }
  ],
  "name": "ample_sfdc_flow_action",
  "namespace": "",
  "sfdcLoginUrl": "https://login.salesforce.com",
  "sourceApiVersion": "62.0",
  "packageAliases": {
    "AmpleFlowEnrichAndSequence": "0HoQy0000000hZdKAI",
    "AmplemarketEnrichAndSequenceFlow": "0HoQy0000000hbFKAQ"
  }
}